AUTHORS.txt
CHANGELOG.txt
LICENSE.txt
README.txt
setup.py
pyutilib/__init__.py
pyutilib.autodist.egg-info/PKG-INFO
pyutilib.autodist.egg-info/SOURCES.txt
pyutilib.autodist.egg-info/dependency_links.txt
pyutilib.autodist.egg-info/namespace_packages.txt
pyutilib.autodist.egg-info/top_level.txt
pyutilib/autodist/__init__.py
pyutilib/autodist/autodist.py
pyutilib/autodist/autodist_core.py
pyutilib/autodist/makensis.py
scripts/download.py
scripts/unix2dos.py
scripts/unzip.py
scripts/zip.py