Metadata-Version: 1.0
Name: pyutilib.autodist
Version: 1.0
Summary: PyUtilib automated Python distribution utility.
Home-page: https://software.sandia.gov/svn/public/pyutilib/pyutilib.autosidt
Author: John D. Siirola
Author-email: jdsiiro@sandia.gov
License: BSD
Keywords: utility
Platform: any
Classifier: Development Status :: 4 - Beta
Classifier: Intended Audience :: End Users/Desktop
Classifier: License :: OSI Approved :: BSD License
Classifier: Natural Language :: English
Classifier: Operating System :: Microsoft :: Windows
Classifier: Operating System :: Unix
Classifier: Programming Language :: Python
Classifier: Programming Language :: Unix Shell
Classifier: Topic :: Scientific/Engineering :: Mathematics
Classifier: Topic :: Software Development :: Libraries :: Python Modules
